{"assets":{"4B010A2A7CA60FFC67D65B7A72FD4370":{"type":"texture","index":114,"assetRequest":{"type":"slide","state":"incoming","slide":"825E4FCD-1385-4BBA-96AB-A43BF2886A7A"},"url":"assets/4B010A2A7CA60FFC67D65B7A72FD4370.png","width":1024,"height":768},"C10D63313BA68B5CB8E735BB2E07DE98":{"type":"texture","index":113,"assetRequest":{"type":"slide","state":"outgoing","slide":"D0AC57C2-4503-46CB-8071-5871F1DE6F45"},"url":"assets/C10D63313BA68B5CB8E735BB2E07DE98.png","width":1024,"height":768}},"events":[{"effects":[{"beginTime":0,"baseLayer":{"animations":[],"initialState":{"affineTransform":[1,0,0,1,0,0],"masksToBounds":true,"rotation":0,"scale":1,"position":{"pointX":512,"pointY":384},"width":1024,"sublayerTransform":[1,0,0,0,0,1,0,0,0,0,1,0,0,0,0,1],"contentsRect":{"y":0,"x":0,"width":1,"height":1},"opacity":1,"edgeAntialiasingMask":0,"height":768,"hidden":false,"anchorPoint":{"pointX":0.5,"pointY":0.5}},"objectID":"0","layers":[{"animations":[],"initialState":{"affineTransform":[1,0,0,1,0,0],"masksToBounds":false,"rotation":0,"scale":1,"position":{"pointX":512,"pointY":384},"width":1024,"sublayerTransform":[1,0,0,0,0,1,0,0,0,0,1,-0.0004922987690640373,0,0,0,1],"contentsRect":{"y":0,"x":0,"width":1,"height":1},"opacity":1,"edgeAntialiasingMask":15,"height":768,"hidden":false,"anchorPoint":{"pointX":0.5,"pointY":0.5}},"layers":[{"animations":[],"layers":[],"initialState":{"affineTransform":[1,0,0,1,0,0],"masksToBounds":false,"rotation":0,"scale":1,"position":{"pointX":512,"pointY":384},"width":1024,"sublayerTransform":[1,0,0,0,0,1,0,0,0,0,1,0,0,0,0,1],"contentsRect":{"y":0,"x":0,"width":1,"height":1},"opacity":1,"edgeAntialiasingMask":0,"height":768,"hidden":false,"anchorPoint":{"pointX":0.5,"pointY":0.5}},"texture":"4B010A2A7CA60FFC67D65B7A72FD4370"},{"animations":[{"from":{"scalar":false},"beginTime":0,"repeatCount":0,"fillMode":"both","property":"hidden","duration":0.01,"to":{"scalar":true}}],"layers":[],"initialState":{"affineTransform":[1,0,0,1,0,0],"masksToBounds":false,"rotation":0,"scale":1,"position":{"pointX":512,"pointY":384},"width":1024,"sublayerTransform":[1,0,0,0,0,1,0,0,0,0,1,0,0,0,0,1],"contentsRect":{"y":0,"x":0,"width":1,"height":1},"opacity":1,"edgeAntialiasingMask":0,"height":768,"hidden":false,"anchorPoint":{"pointX":0.5,"pointY":0.5}},"texture":"C10D63313BA68B5CB8E735BB2E07DE98"}]}]},"effects":[],"duration":0.01,"type":"transition","name":"none","objectID":"0"}],"automaticPlay":false,"hyperlinks":[],"accessibility":[{"text":"PubMed ID or PubMed検索語を入力","targetRectangle":{"y":82,"x":49,"width":668.7239999999999,"height":49.78170776367188}},{"text":"もしくは","targetRectangle":{"y":308.9726747274399,"x":335.8943195343018,"width":144,"height":35.9999635219574}},{"text":"pasted-image.png","targetRectangle":{"y":196.1710968017578,"x":79.58544921875,"width":864.8291015625,"height":491.6578063964844}},{"text":"①","targetRectangle":{"y":257.6258850097656,"x":259.1355285644531,"width":40,"height":39.99995946884155}},{"text":"droppedImage.png","targetRectangle":{"y":745,"x":698,"width":80,"height":15}},{"text":"PubMed ID","targetRectangle":{"y":256.1480112075806,"x":304.8723118305206,"width":174.24,"height":42.95574951171875}},{"text":"ライフサイエンス統合データベースセンター","targetRectangle":{"y":748,"x":778.6799826049805,"width":237.1199999999999,"height":11.99998784065247}},{"text":"②","targetRectangle":{"y":358,"x":276.0112609863281,"width":40,"height":39.99995946884155}},{"text":"PubMed検索語","targetRectangle":{"y":355.5221261978149,"x":322.5327529907227,"width":239.5799999999999,"height":42.95574951171875}}],"baseLayer":{"animations":[],"initialState":{"affineTransform":[1,0,0,1,0,0],"masksToBounds":true,"rotation":0,"scale":1,"position":{"pointX":512,"pointY":384},"width":1024,"sublayerTransform":[1,0,0,0,0,1,0,0,0,0,1,0,0,0,0,1],"contentsRect":{"y":0,"x":0,"width":1,"height":1},"opacity":1,"edgeAntialiasingMask":0,"height":768,"hidden":false,"anchorPoint":{"pointX":0.5,"pointY":0.5}},"objectID":"0","layers":[{"animations":[],"initialState":{"affineTransform":[1,0,0,1,0,0],"masksToBounds":false,"rotation":0,"scale":1,"position":{"pointX":512,"pointY":384},"width":1024,"sublayerTransform":[1,0,0,0,0,1,0,0,0,0,1,-0.0004922987690640373,0,0,0,1],"contentsRect":{"y":0,"x":0,"width":1,"height":1},"opacity":1,"edgeAntialiasingMask":15,"height":768,"hidden":false,"anchorPoint":{"pointX":0.5,"pointY":0.5}},"layers":[{"animations":[],"layers":[],"initialState":{"affineTransform":[1,0,0,1,0,0],"masksToBounds":false,"rotation":0,"scale":1,"position":{"pointX":512,"pointY":384},"width":1024,"sublayerTransform":[1,0,0,0,0,1,0,0,0,0,1,0,0,0,0,1],"contentsRect":{"y":0,"x":0,"width":1,"height":1},"opacity":1,"edgeAntialiasingMask":0,"height":768,"hidden":false,"anchorPoint":{"pointX":0.5,"pointY":0.5}},"texture":"C10D63313BA68B5CB8E735BB2E07DE98"}]}]}}]}